Metadata-Version: 2.1
Name: pysentiment2
Version: 0.1.1
Summary: Sentiment Analysis in Python using a Dictionary Approach
Home-page: https://github.com/nickderobertis/pysentiment
Author: Nick DeRobertis
Author-email: whoopnip@gmail.com
License: MIT
Project-URL: Code, https://github.com/nickderobertis/pysentiment
Project-URL: Documentation, https://nickderobertis.github.io/pysentiment
Platform: UNKNOWN
Classifier: Development Status :: 3 - Alpha
Classifier: Intended Audience :: Developers
Classifier: Programming Language :: Python :: 3.6
Classifier: Programming Language :: Python :: 3.7
Requires-Dist: pandas
Requires-Dist: nltk (>=2.0)
